testing.parity-1.0.7-py3.7-nspkg.pth
testing/ethminer.py
testing/ganache.py
testing/parity.py
testing/tenderly.py
testing.parity-1.0.7.dist-info/LICENSE
testing.parity-1.0.7.dist-info/METADATA
testing.parity-1.0.7.dist-info/WHEEL
testing.parity-1.0.7.dist-info/namespace_packages.txt
testing.parity-1.0.7.dist-info/top_level.txt
testing.parity-1.0.7.dist-info/RECORD
