Metadata-Version: 2.1
Name: testing.parity
Version: 1.0.7
Summary: automatically setups a parity-ethereum instance, and destroys it after testing
Home-page: https://github.com/tristan/testing.parity
Author: Tristan King
Author-email: mail@tristan.sh
License: Apache License 2.0
Platform: UNKNOWN
Classifier: Development Status :: 4 - Beta
Classifier: Intended Audience :: Developers
Classifier: License :: OSI Approved :: Apache Software License
Classifier: Programming Language :: Python
Classifier: Programming Language :: Python :: 2.6
Classifier: Programming Language :: Python :: 2.7
Classifier: Programming Language :: Python :: 3.2
Classifier: Programming Language :: Python :: 3.3
Classifier: Programming Language :: Python :: 3.4
Classifier: Programming Language :: Python :: 3.5
Classifier: Topic :: Database
Classifier: Topic :: Software Development
Classifier: Topic :: Software Development :: Testing
Requires-Dist: testing.common.database (>=1.1.0)
Requires-Dist: py-ecc
Requires-Dist: ethereum
